<NODE><INFO>rendered by Everything::XML.pm</INFO>
	<author_user table="node" type="user">root</author_user>
	<core table="node">R</core>
	<displaytype table="htmlpage">edit</displaytype>
	<package table="node">0</package>
	<page table="htmlpage">title:[{textfield:title}] maintained by:[{node_menu:author_user,user,usergroup}]&lt;br&gt;
Maintains: [{node_menu:maintain_nodetype}]&lt;br&gt;
maintaintype:[{textfield:maintaintype}](create, update, or delete)&lt;br&gt;

&lt;table width=100%&gt;
&lt;tr&gt;
&lt;td width=90%&gt;
&lt;p&gt;&lt;FONT SIZE=2&gt;&lt;b&gt;Edit the code:&lt;/b&gt;&lt;/FONT&gt;&lt;br&gt;
[{textarea:code}]&lt;/td&gt;
&lt;td width=10%&gt;&lt;font size=2&gt;[%
my $N = $DB-&gt;getNodeById($$NODE{maintain_nodetype});
my $str;
$str .= "&lt;li&gt;";
$str .= join "\n&lt;li&gt;", getFields;

my @tables = @{ $DB-&gt;getNodetypeTables($$NODE{maintain_nodetype}) };
foreach (@tables) {
  $str .="\n&lt;li&gt;";
  $str .= join "\n&lt;li&gt;", getFields($_);
}
$str;



%]&lt;/font&gt;&lt;/td&gt;

&lt;/tr&gt;&lt;/table&gt;
</page>
	<pagetype_nodetype table="htmlpage" type="nodetype">maintenance</pagetype_nodetype>
	<parent_container table="htmlpage" type="container">formcontainer</parent_container>
	<reputation table="node">0</reputation>
	<title table="node">maintenance edit page</title>
	<type_nodetype table="node" type="nodetype">htmlpage</type_nodetype>
</NODE>