<NODE export_version="0.5" nodetype="nodelet" title="Server Statistics">
  <field type="noderef" type_nodetype="user,nodetype" name="author_user">root</field>
  <field type="literal_value" name="authoraccess">iiii</field>
  <field type="literal_value" name="dynamicauthor_permission">-1</field>
  <field type="literal_value" name="dynamicgroup_permission">-1</field>
  <field type="literal_value" name="dynamicguest_permission">-1</field>
  <field type="literal_value" name="dynamicother_permission">-1</field>
  <field type="literal_value" name="group_usergroup">-1</field>
  <field type="literal_value" name="groupaccess">iiii-</field>
  <field type="literal_value" name="guestaccess">iiii-</field>
  <field type="noderef" type_nodetype="location,nodetype" name="loc_location">nodelet</field>
  <field type="literal_value" name="mini_nodelet">0</field>
  <field type="literal_value" name="nlcode">[{serverstats}]</field>
  <field type="literal_value" name="nlgoto">0</field>
  <field type="literal_value" name="nltext">Sat Dec 30 00:04:03 EST 2000
&lt;br>up 2 days 2:56&lt;br>0.74,  0.52,  0.35, &lt;br></field>
  <field type="literal_value" name="otheraccess">iiii-</field>
  <field type="noderef" type_nodetype="container,nodetype" name="parent_container">general nodelet container</field>
  <field type="literal_value" name="title">Server Statistics</field>
  <field type="noderef" type_nodetype="nodetype,nodetype" name="type_nodetype">nodelet</field>
  <field type="literal_value" name="updateinterval">5</field>
</NODE>
